rebrick/__init__.py
rebrick/api_lego.py
rebrick/api_users.py
rebrick/config.py
rebrick/objects.py
rebrick/rebrick.py
rebrick/request.py
rebrick-0.4.0.dist-info/LICENSE
rebrick-0.4.0.dist-info/METADATA
rebrick-0.4.0.dist-info/WHEEL
rebrick-0.4.0.dist-info/top_level.txt
rebrick-0.4.0.dist-info/RECORD
