Metadata-Version: 2.1
Name: rebrick
Version: 0.4.0
Summary: Python access to Rebrickable API.
Home-page: https://github.com/xxao/rebrick
Author: Martin Strohalm
Author-email: 
License: MIT
Classifier: Development Status :: 3 - Alpha
Classifier: Programming Language :: Python :: 3 :: Only
Classifier: Operating System :: OS Independent
Classifier: Topic :: Utilities
Classifier: Intended Audience :: Other Audience
License-File: LICENSE
